pygame_menu/__init__.py
pygame_menu/_base.py
pygame_menu/_decorator.py
pygame_menu/_scrollarea.py
pygame_menu/_types.py
pygame_menu/_widgetmanager.py
pygame_menu/baseimage.py
pygame_menu/controls.py
pygame_menu/events.py
pygame_menu/font.py
pygame_menu/locals.py
pygame_menu/menu.py
pygame_menu/py.typed
pygame_menu/sound.py
pygame_menu/themes.py
pygame_menu/utils.py
pygame_menu/version.py
pygame_menu/__pyinstaller/__init__.py
pygame_menu/__pyinstaller/hook-pygame_menu.py
pygame_menu/examples/__init__.py
pygame_menu/examples/_resources.py
pygame_menu/examples/game_selector.py
pygame_menu/examples/multi_input.py
pygame_menu/examples/scroll_menu.py
pygame_menu/examples/simple.py
pygame_menu/examples/timer_clock.py
pygame_menu/examples/window_resize.py
pygame_menu/examples/other/__init__.py
pygame_menu/examples/other/calculator.py
pygame_menu/examples/other/dynamic_button_append.py
pygame_menu/examples/other/dynamic_widget_update.py
pygame_menu/examples/other/image_background.py
pygame_menu/examples/other/maze.py
pygame_menu/examples/other/scrollbar.py
pygame_menu/examples/other/scrollbar_area.py
pygame_menu/examples/other/ui_solar_system.py
pygame_menu/examples/other/widget_positioning.py
pygame_menu/resources/fonts/8bit.ttf
pygame_menu/resources/fonts/FiraCode-Bold.ttf
pygame_menu/resources/fonts/FiraCode-Regular.ttf
pygame_menu/resources/fonts/FiraMono-BoldItalic.ttf
pygame_menu/resources/fonts/FiraMono-Italic.ttf
pygame_menu/resources/fonts/LICENSE_DIGITAL.txt
pygame_menu/resources/fonts/LICENSE_FiraCode.txt
pygame_menu/resources/fonts/LICENSE_OPENSANS.txt
pygame_menu/resources/fonts/LICENSE_PTSERIF.txt
pygame_menu/resources/fonts/bebas.ttf
pygame_menu/resources/fonts/comic_neue.ttf
pygame_menu/resources/fonts/digital.ttf
pygame_menu/resources/fonts/franchise.ttf
pygame_menu/resources/fonts/helvetica.ttf
pygame_menu/resources/fonts/munro.ttf
pygame_menu/resources/fonts/nevis.ttf
pygame_menu/resources/fonts/opensans_bold.ttf
pygame_menu-4.5.3.dist-info/LICENSE
pygame_menu-4.5.3.dist-info/METADATA
pygame_menu-4.5.3.dist-info/WHEEL
pygame_menu-4.5.3.dist-info/entry_points.txt
pygame_menu-4.5.3.dist-info/top_level.txt
pygame_menu-4.5.3.dist-info/RECORD
